{
  "cards": [
    {
      "id": 0,
      "name": "Biedna Pierdolona Piechota",
      "power": 1,
      "description": "",
      "pictureFilename": "nor_poor_infantry.webp",
      "faction": 1,
      "range": 1,
      "function": "std",
      "ability": "bond"
    },
    {
      "id": 1,
      "name": "Biedna Pierdolona Piechota",
      "power": 1,
      "description": "",
      "pictureFilename": "nor_poor_infantry_1.webp",
      "faction": 1,
      "range": 1,
      "function": "std",
      "ability": "bond"
    },
    {
      "id": 2,
      "name": "Biedna Pierdolona Piechota",
      "power": 1,
      "description": "",
      "pictureFilename": "nor_poor_infantry_2.webp",
      "faction": 1,
      "range": 1,
      "function": "std",
      "ability": "bond"
    },
    {
      "id": 3,
      "name": "Mistrz Oblężeń z Kaedwen",
      "power": 1,
      "description": "",
      "pictureFilename": "nor_kaedwen_siege.webp",
      "faction": 1,
      "range": 2,
      "function": "std",
      "ability": "morale"
    },
    {
      "id": 4,
      "name": "Mistrz Oblężeń z Kaedwen",
      "power": 1,
      "description": "",
      "pictureFilename": "nor_kaedwen_siege_1.webp",
      "faction": 1,
      "range": 2,
      "function": "std",
      "ability": "morale"
    },
    {
      "id": 5,
      "name": "Mistrz Oblężeń z Kaedwen",
      "power": 1,
      "description": "",
      "pictureFilename": "nor_kaedwen_siege_2.webp",
      "faction": 1,
      "range": 2,
      "function": "std",
      "ability": "morale"
    },
    {
      "id": 6,
      "name": "Redański Piechur",
      "power": 1,
      "description": "",
      "pictureFilename": "nor_redania.webp",
      "faction": 1,
      "range": 1,
      "function": "std",
      "ability": "none"
    },
    {
      "id": 7,
      "name": "Redański Piechur",
      "power": 1,
      "description": "",
      "pictureFilename": "nor_redania_1.webp",
      "faction": 1,
      "range": 1,
      "function": "std",
      "ability": "none"
    },
    {
      "id": 8,
      "name": "Talar",
      "power": 1,
      "description": "",
      "pictureFilename": "nor_thaler.webp",
      "faction": 1,
      "range": 2,
      "function": "std",
      "ability": "spy"
    },
    {
      "id": 9,
      "name": "Yarpen Zigrin",
      "power": 2,
      "description": "",
      "pictureFilename": "nor_yarpen.webp",
      "faction": 1,
      "range": 1,
      "function": "std",
      "ability": "none"
    },
    {
      "id": 10,
      "name": "Komandor Niebieskich Pasów",
      "power": 4,
      "description": "",
      "pictureFilename": "nor_blue_stripes.webp",
      "faction": 1,
      "range": 1,
      "function": "std",
      "ability": "bond"
    },
    {
      "id": 11,
      "name": "Komandor Niebieskich Pasów",
      "power": 4,
      "description": "",
      "pictureFilename": "nor_blue_stripes_1.webp",
      "faction": 1,
      "range": 1,
      "function": "std",
      "ability": "bond"
    },
    {
      "id": 12,
      "name": "Komandor Niebieskich Pasów",
      "power": 4,
      "description": "",
      "pictureFilename": "nor_blue_stripes_2.webp",
      "faction": 1,
      "range": 1,
      "function": "std",
      "ability": "bond"
    },
    {
      "id": 13,
      "name": "Sabrina Glevessig",
      "power": 4,
      "description": "",
      "pictureFilename": "nor_sabrina.webp",
      "faction": 1,
      "range": 2,
      "function": "std",
      "ability": "none"
    },
    {
      "id": 14,
      "name": "Sheldon Skaggs",
      "power": 4,
      "description": "",
      "pictureFilename": "nor_sheldon.webp",
      "faction": 1,
      "range": 2,
      "function": "std",
      "ability": "none"
    },
    {
      "id": 15,
      "name": "Sigismund Dijkstra",
      "power": 4,
      "description": "",
      "pictureFilename": "nor_dijktra.webp",
      "faction": 1,
      "range": 1,
      "function": "std",
      "ability": "spy"
    },
    {
      "id": 16,
      "name": "Rębacze z Crinfrid",
      "power": 5,
      "description": "",
      "pictureFilename": "nor_crinfrid.webp",
      "faction": 1,
      "range": 2,
      "function": "std",
      "ability": "bond"
    },
    {
      "id": 17,
      "name": "Rębacze z Crinfrid",
      "power": 5,
      "description": "",
      "pictureFilename": "nor_crinfrid_1.webp",
      "faction": 1,
      "range": 2,
      "function": "std",
      "ability": "bond"
    },
    {
      "id": 18,
      "name": "Rębacze z Crinfrid",
      "power": 5,
      "description": "",
      "pictureFilename": "nor_crinfrid_2.webp",
      "faction": 1,
      "range": 2,
      "function": "std",
      "ability": "bond"
    },
    {
      "id": 19,
      "name": "Medyczka Burej Chorągwi",
      "power": 5,
      "description": "",
      "pictureFilename": "nor_banner_nurse.webp",
      "faction": 1,
      "range": 2,
      "function": "std",
      "ability": "medic"
    },
    {
      "id": 20,
      "name": "Keira Metz",
      "power": 5,
      "description": "",
      "pictureFilename": "nor_keira.webp",
      "faction": 1,
      "range": 2,
      "function": "std",
      "ability": "none"
    },
    {
      "id": 21,
      "name": "Stennis",
      "power": 5,
      "description": "",
      "pictureFilename": "nor_stennis.webp",
      "faction": 1,
      "range": 1,
      "function": "std",
      "ability": "spy"
    },
    {
      "id": 22,
      "name": "Zygfryd z Denesle",
      "power": 5,
      "description": "",
      "pictureFilename": "nor_siegfried.webp",
      "faction": 1,
      "range": 1,
      "function": "std",
      "ability": "none"
    },
    {
      "id": 23,
      "name": "Sheala de Tancarville",
      "power": 5,
      "description": "",
      "pictureFilename": "nor_sheala.webp",
      "faction": 1,
      "range": 2,
      "function": "std",
      "ability": "none"
    },
    {
      "id": 24,
      "name": "Ves",
      "power": 5,
      "description": "",
      "pictureFilename": "nor_ves.webp",
      "faction": 1,
      "range": 1,
      "function": "std",
      "ability": "none"
    },
    {
      "id": 25,
      "name": "Balista",
      "power": 6,
      "description": "",
      "pictureFilename": "nor_ballista.webp",
      "faction": 1,
      "range": 2,
      "function": "std",
      "ability": "none"
    },
    {
      "id": 26,
      "name": "Balista",
      "power": 6,
      "description": "",
      "pictureFilename": "nor_ballista_1.webp",
      "faction": 1,
      "range": 2,
      "function": "std",
      "ability": "none"
    },
    {
      "id": 27,
      "name": "Detmold",
      "power": 6,
      "description": "",
      "pictureFilename": "nor_dethmold.webp",
      "faction": 1,
      "range": 2,
      "function": "std",
      "ability": "none"
    },
    {
      "id": 28,
      "name": "Wieża Oblężnicza",
      "power": 6,
      "description": "",
      "pictureFilename": "nor_siege_tower.webp",
      "faction": 1,
      "range": 2,
      "function": "std",
      "ability": "none"
    },
    {
      "id": 29,
      "name": "Trebusz",
      "power": 6,
      "description": "",
      "pictureFilename": "nor_trebuchet.webp",
      "faction": 1,
      "range": 2,
      "function": "std",
      "ability": "none"
    },
    {
      "id": 30,
      "name": "Trebusz",
      "power": 6,
      "description": "",
      "pictureFilename": "nor_trebuchet_1.webp",
      "faction": 1,
      "range": 2,
      "function": "std",
      "ability": "none"
    },
    {
      "id": 31,
      "name": "Katapulta",
      "power": 8,
      "description": "",
      "pictureFilename": "nor_catapult.webp",
      "faction": 1,
      "range": 2,
      "function": "std",
      "ability": "bond"
    },
    {
      "id": 32,
      "name": "Katapulta",
      "power": 8,
      "description": "",
      "pictureFilename": "nor_catapult_1.webp",
      "faction": 1,
      "range": 2,
      "function": "std",
      "ability": "bond"
    },
    {
      "id": 33,
      "name": "Esterad Thyssen",
      "power": 10,
      "description": "",
      "pictureFilename": "nor_esterad.webp",
      "faction": 1,
      "range": 1,
      "function": "hero",
      "ability": "none"
    },
    {
      "id": 34,
      "name": "Jan Natalis",
      "power": 10,
      "description": "",
      "pictureFilename": "nor_natalis.webp",
      "faction": 1,
      "range": 1,
      "function": "hero",
      "ability": "none"
    },
    {
      "id": 35,
      "name": "Vernon Roche",
      "power": 10,
      "description": "",
      "pictureFilename": "nor_vernon.webp",
      "faction": 1,
      "range": 1,
      "function": "hero",
      "ability": "none"
    },
    {
      "id": 36,
      "name": "Filippa Eilhart",
      "power": 10,
      "description": "",
      "pictureFilename": "nor_philippa.webp",
      "faction": 1,
      "range": 2,
      "function": "hero",
      "ability": "none"
    },
    {
      "id": 37,
      "name": "Tajemiczny Elf",
      "power": 0,
      "description": "",
      "pictureFilename": "neu_avallach.webp",
      "faction": 1,
      "range": 1,
      "function": "hero",
      "ability": "spy"
    },
    {
      "id": 38,
      "name": "Geralt z Rivii",
      "power": 15,
      "description": "",
      "pictureFilename": "neu_geralt.webp",
      "faction": 1,
      "range": 1,
      "function": "hero",
      "ability": "none"
    },
    {
      "id": 39,
      "name": "Cirilla Fiona Elen Riannon",
      "power": 15,
      "description": "",
      "pictureFilename": "neu_ciri.webp",
      "faction": 1,
      "range": 1,
      "function": "hero",
      "ability": "none"
    },
    {
      "id": 40,
      "name": "Jaskier",
      "power": 2,
      "description": "",
      "pictureFilename": "neu_dandelion.webp",
      "faction": 1,
      "range": 1,
      "function": "std",
      "ability": "horn"
    },
    {
      "id": 41,
      "name": "Emiel Regis Rohellec Terzieff-Godefroy",
      "power": 5,
      "description": "",
      "pictureFilename": "neu_emiel.webp",
      "faction": 1,
      "range": 1,
      "function": "std",
      "ability": "none"
    },
    {
      "id": 42,
      "name": "Triss Merigold",
      "power": 7,
      "description": "",
      "pictureFilename": "neu_triss.webp",
      "faction": 1,
      "range": 1,
      "function": "hero",
      "ability": "none"
    },
    {
      "id": 43,
      "name": "Vesemir",
      "power": 6,
      "description": "",
      "pictureFilename": "neu_vesemir.webp",
      "faction": 1,
      "range": 1,
      "function": "std",
      "ability": "none"
    },
    {
      "id": 44,
      "name": "Villentretenmerth",
      "power": 6,
      "description": "",
      "pictureFilename": "neu_villen.webp",
      "faction": 1,
      "range": 1,
      "function": "std",
      "ability": "scorch"
    },
    {
      "id": 45,
      "name": "Yennefer z Vengerbergu",
      "power": 7,
      "description": "",
      "pictureFilename": "neu_yennefer.webp",
      "faction": 1,
      "range": 2,
      "function": "hero",
      "ability": "medic"
    },
    {
      "id": 46,
      "name": "Zoltan Chivay",
      "power": 5,
      "description": "",
      "pictureFilename": "neu_zoltan.webp",
      "faction": 1,
      "range": 1,
      "function": "std",
      "ability": "none"
    },
    {
      "id": 47,
      "name": "Olgierd von Everec",
      "power": 6,
      "description": "",
      "pictureFilename": "neu_olgierd.webp",
      "faction": 1,
      "range": 1,
      "function": "std",
      "ability": "morale"
    },
    {
      "id": 48,
      "name": "Gaunter O'Dim",
      "power": 2,
      "description": "",
      "pictureFilename": "neu_mrmirror.webp",
      "faction": 1,
      "range": 2,
      "function": "std",
      "ability": "muster"
    },
    {
      "id": 49,
      "name": "Gaunter O'Dim: Cień",
      "power": 4,
      "description": "",
      "pictureFilename": "neu_mrmirror_foglet.webp",
      "faction": 1,
      "range": 1,
      "function": "std",
      "ability": "muster"
    },
    {
      "id": 50,
      "name": "Gaunter O'Dim: Cień",
      "power": 4,
      "description": "",
      "pictureFilename": "neu_mrmirror_foglet.webp",
      "faction": 1,
      "range": 1,
      "function": "std",
      "ability": "muster"
    },
    {
      "id": 51,
      "name": "Gaunter O'Dim: Cień",
      "power": 4,
      "description": "",
      "pictureFilename": "neu_mrmirror_foglet.webp",
      "faction": 1,
      "range": 1,
      "function": "std",
      "ability": "muster"
    },
    {
      "id": 52,
      "name": "Róg Dowódcy",
      "power": 0,
      "description": "",
      "pictureFilename": "spc_horn.webp",
      "faction": 1,
      "range": 0,
      "function": "horn",
      "ability": "none"
    },
    {
      "id": 53,
      "name": "Róg Dowódcy",
      "power": 0,
      "description": "",
      "pictureFilename": "spc_horn.webp",
      "faction": 1,
      "range": 0,
      "function": "horn",
      "ability": "none"
    },
    {
      "id": 54,
      "name": "Róg Dowódcy",
      "power": 0,
      "description": "",
      "pictureFilename": "spc_horn.webp",
      "faction": 1,
      "range": 0,
      "function": "horn",
      "ability": "none"
    },
    {
      "id": 55,
      "name": "Manekin do ćwiczeń",
      "power": 0,
      "description": "",
      "pictureFilename": "spc_dummy.webp",
      "faction": 1,
      "range": 0,
      "function": "decoy",
      "ability": "none"
    },
    {
      "id": 56,
      "name": "Manekin do ćwiczeń",
      "power": 0,
      "description": "",
      "pictureFilename": "spc_dummy.webp",
      "faction": 1,
      "range": 0,
      "function": "decoy",
      "ability": "none"
    },
    {
      "id": 57,
      "name": "Manekin do ćwiczeń",
      "power": 0,
      "description": "",
      "pictureFilename": "spc_dummy.webp",
      "faction": 1,
      "range": 0,
      "function": "decoy",
      "ability": "none"
    },
    {
      "id": 58,
      "name": "Pożoga",
      "power": 0,
      "description": "",
      "pictureFilename": "spc_scorch.webp",
      "faction": 1,
      "range": 0,
      "function": "scorch",
      "ability": "none"
    },
    {
      "id": 59,
      "name": "Pożoga",
      "power": 0,
      "description": "",
      "pictureFilename": "spc_scorch.webp",
      "faction": 1,
      "range": 0,
      "function": "scorch",
      "ability": "none"
    },
    {
      "id": 60,
      "name": "Pożoga",
      "power": 0,
      "description": "",
      "pictureFilename": "spc_scorch.webp",
      "faction": 1,
      "range": 0,
      "function": "scorch",
      "ability": "none"
    },
    {
      "id": 61,
      "name": "Trzaskający mróz",
      "power": 0,
      "description": "",
      "pictureFilename": "spc_frost.webp",
      "faction": 1,
      "range": 0,
      "function": "frost",
      "ability": "none"
    },
    {
      "id": 62,
      "name": "Trzaskający mróz",
      "power": 0,
      "description": "",
      "pictureFilename": "spc_frost.webp",
      "faction": 1,
      "range": 0,
      "function": "frost",
      "ability": "none"
    },
    {
      "id": 63,
      "name": "Trzaskający mróz",
      "power": 0,
      "description": "",
      "pictureFilename": "spc_frost.webp",
      "faction": 1,
      "range": 0,
      "function": "frost",
      "ability": "none"
    },
    {
      "id": 64,
      "name": "Gęsta mgła",
      "power": 0,
      "description": "",
      "pictureFilename": "spc_fog.webp",
      "faction": 1,
      "range": 0,
      "function": "fog",
      "ability": "none"
    },
    {
      "id": 65,
      "name": "Gęsta mgła",
      "power": 0,
      "description": "",
      "pictureFilename": "spc_fog.webp",
      "faction": 1,
      "range": 0,
      "function": "fog",
      "ability": "none"
    },
    {
      "id": 66,
      "name": "Gęsta mgła",
      "power": 0,
      "description": "",
      "pictureFilename": "spc_fog.webp",
      "faction": 1,
      "range": 0,
      "function": "fog",
      "ability": "none"
    },
    {
      "id": 67,
      "name": "Czyste niebo",
      "power": 0,
      "description": "",
      "pictureFilename": "spc_clearsky.webp",
      "faction": 1,
      "range": 0,
      "function": "clear",
      "ability": "none"
    },
    {
      "id": 68,
      "name": "Czyste niebo",
      "power": 0,
      "description": "",
      "pictureFilename": "spc_clearsky.webp",
      "faction": 1,
      "range": 0,
      "function": "clear",
      "ability": "none"
    },
    {
      "id": 69,
      "name": "Czyste niebo",
      "power": 0,
      "description": "",
      "pictureFilename": "spc_clearsky.webp",
      "faction": 1,
      "range": 0,
      "function": "clear",
      "ability": "none"
    },
    {
      "id": 70,
      "name": "Ghul",
      "power": 1,
      "description": "",
      "pictureFilename": "nml_ghoul.webp",
      "faction": 2,
      "range": 1,
      "function": "std",
      "ability": "muster"
    },
    {
      "id": 71,
      "name": "Ghul",
      "power": 1,
      "description": "",
      "pictureFilename": "nml_ghoul_1.webp",
      "faction": 2,
      "range": 1,
      "function": "std",
      "ability": "muster"
    },
    {
      "id": 72,
      "name": "Ghul",
      "power": 1,
      "description": "",
      "pictureFilename": "nml_ghoul_2.webp",
      "faction": 2,
      "range": 1,
      "function": "std",
      "ability": "muster"
    },
    {
      "id": 73,
      "name": "Harbia Celaeno",
      "power": 2,
      "description": "",
      "pictureFilename": "nml_celaeno_harpy.webp",
      "faction": 2,
      "range": 1,
      "function": "std",
      "ability": "none"
    },
    {
      "id": 74,
      "name": "Kuroliszek",
      "power": 2,
      "description": "",
      "pictureFilename": "nml_cockatrice.webp",
      "faction": 2,
      "range": 2,
      "function": "std",
      "ability": "none"
    },
    {
      "id": 75,
      "name": "Endriaga",
      "power": 2,
      "description": "",
      "pictureFilename": "nml_endrega.webp",
      "faction": 2,
      "range": 2,
      "function": "std",
      "ability": "none"
    },
    {
      "id": 76,
      "name": "Mglak",
      "power": 2,
      "description": "",
      "pictureFilename": "nml_fogling.webp",
      "faction": 2,
      "range": 1,
      "function": "std",
      "ability": "none"
    },
    {
      "id": 77,
      "name": "Gargulec",
      "power": 2,
      "description": "",
      "pictureFilename": "nml_gargoyle.webp",
      "faction": 2,
      "range": 2,
      "function": "std",
      "ability": "none"
    },
    {
      "id": 78,
      "name": "Harpia",
      "power": 2,
      "description": "",
      "pictureFilename": "nml_harpy.webp",
      "faction": 2,
      "range": 1,
      "function": "std",
      "ability": "none"
    },
    {
      "id": 79,
      "name": "Nekker",
      "power": 2,
      "description": "",
      "pictureFilename": "nml_nekker.webp",
      "faction": 2,
      "range": 1,
      "function": "std",
      "ability": "muster"
    },
    {
      "id": 80,
      "name": "Nekker",
      "power": 2,
      "description": "",
      "pictureFilename": "nml_nekker_1.webp",
      "faction": 2,
      "range": 1,
      "function": "std",
      "ability": "muster"
    },
    {
      "id": 81,
      "name": "Nekker",
      "power": 2,
      "description": "",
      "pictureFilename": "nml_nekker_2.webp",
      "faction": 2,
      "range": 1,
      "function": "std",
      "ability": "muster"
    },
    {
      "id": 82,
      "name": "Wiwerna",
      "power": 2,
      "description": "",
      "pictureFilename": "nml_wyvern.webp",
      "faction": 2,
      "range": 2,
      "function": "std",
      "ability": "none"
    },
    {
      "id": 83,
      "name": "Krabopająk",
      "power": 4,
      "description": "",
      "pictureFilename": "nml_arachas.webp",
      "faction": 2,
      "range": 1,
      "function": "std",
      "ability": "muster"
    },
    {
      "id": 84,
      "name": "Krabopająk",
      "power": 4,
      "description": "",
      "pictureFilename": "nml_arachas_1.webp",
      "faction": 2,
      "range": 1,
      "function": "std",
      "ability": "muster"
    },
    {
      "id": 85,
      "name": "Krabopająk",
      "power": 4,
      "description": "",
      "pictureFilename": "nml_arachas_2.webp",
      "faction": 2,
      "range": 1,
      "function": "std",
      "ability": "muster"
    },
    {
      "id": 86,
      "name": "Poroniec",
      "power": 4,
      "description": "",
      "pictureFilename": "nml_poroniec.webp",
      "faction": 2,
      "range": 1,
      "function": "std",
      "ability": "none"
    },
    {
      "id": 87,
      "name": "Wampiry: Bruxa",
      "power": 4,
      "description": "",
      "pictureFilename": "nml_bruxa.webp",
      "faction": 2,
      "range": 1,
      "function": "std",
      "ability": "muster"
    },
    {
      "id": 88,
      "name": "Wampiry: Ekkima",
      "power": 4,
      "description": "",
      "pictureFilename": "nml_ekkima.webp",
      "faction": 2,
      "range": 1,
      "function": "std",
      "ability": "muster"
    },
    {
      "id": 89,
      "name": "Wampiry: Fleder",
      "power": 4,
      "description": "",
      "pictureFilename": "nml_fleder.webp",
      "faction": 2,
      "range": 1,
      "function": "std",
      "ability": "muster"
    },
    {
      "id": 90,
      "name": "Wampiry: Garkain",
      "power": 4,
      "description": "",
      "pictureFilename": "nml_garkain.webp",
      "faction": 2,
      "range": 1,
      "function": "std",
      "ability": "muster"
    },
    {
      "id": 91,
      "name": "Wampiry: Katakan",
      "power": 5,
      "description": "",
      "pictureFilename": "nml_karakan.webp",
      "faction": 2,
      "range": 1,
      "function": "std",
      "ability": "muster"
    },
    {
      "id": 92,
      "name": "Widłogon",
      "power": 5,
      "description": "",
      "pictureFilename": "nml_forktail.webp",
      "faction": 2,
      "range": 1,
      "function": "std",
      "ability": "none"
    },
    {
      "id": 93,
      "name": "Przeraza",
      "power": 5,
      "description": "",
      "pictureFilename": "nml_frightener.webp",
      "faction": 2,
      "range": 1,
      "function": "std",
      "ability": "none"
    },
    {
      "id": 94,
      "name": "Baba cmentarna",
      "power": 5,
      "description": "",
      "pictureFilename": "nml_gravehag.webp",
      "faction": 2,
      "range": 2,
      "function": "std",
      "ability": "none"
    },
    {
      "id": 95,
      "name": "Gryf",
      "power": 5,
      "description": "",
      "pictureFilename": "nml_gryffin.webp",
      "faction": 2,
      "range": 1,
      "function": "std",
      "ability": "none"
    },
    {
      "id": 96,
      "name": "Lodowy Gigant",
      "power": 5,
      "description": "",
      "pictureFilename": "nml_frost_giant.webp",
      "faction": 2,
      "range": 2,
      "function": "std",
      "ability": "none"
    },
    {
      "id": 97,
      "name": "Morowa Dziewica",
      "power": 5,
      "description": "",
      "pictureFilename": "nml_mighty_maiden.webp",
      "faction": 2,
      "range": 1,
      "function": "std",
      "ability": "none"
    },
    {
      "id": 98,
      "name": "Wilkołak",
      "power": 5,
      "description": "",
      "pictureFilename": "nml_werewolf.webp",
      "faction": 2,
      "range": 1,
      "function": "std",
      "ability": "none"
    },
    {
      "id": 99,
      "name": "Olbrzymi krabopająk",
      "power": 6,
      "description": "",
      "pictureFilename": "nml_arachas_behemoth.webp",
      "faction": 2,
      "range": 2,
      "function": "std",
      "ability": "muster"
    },
    {
      "id": 100,
      "name": "Wiedźma: Kuchta",
      "power": 6,
      "description": "",
      "pictureFilename": "nml_witch_velen.webp",
      "faction": 2,
      "range": 1,
      "function": "std",
      "ability": "muster"
    },
    {
      "id": 101,
      "name": "Wiedźma: Prządka",
      "power": 6,
      "description": "",
      "pictureFilename": "nml_witch_velen_1.webp",
      "faction": 2,
      "range": 1,
      "function": "std",
      "ability": "muster"
    },
    {
      "id": 102,
      "name": "Wiedźma: Szepciucha",
      "power": 6,
      "description": "",
      "pictureFilename": "nml_witch_velen_2.webp",
      "faction": 2,
      "range": 1,
      "function": "std",
      "ability": "muster"
    },
    {
      "id": 103,
      "name": "Żywiołak ziemi",
      "power": 6,
      "description": "",
      "pictureFilename": "nml_earth_elemental.webp",
      "faction": 2,
      "range": 2,
      "function": "std",
      "ability": "none"
    },
    {
      "id": 104,
      "name": "Bies",
      "power": 6,
      "description": "",
      "pictureFilename": "nml_fiend.webp",
      "faction": 2,
      "range": 1,
      "function": "std",
      "ability": "none"
    },
    {
      "id": 105,
      "name": "Żywiołak ognia",
      "power": 6,
      "description": "",
      "pictureFilename": "nml_fire_elemental.webp",
      "faction": 2,
      "range": 2,
      "function": "std",
      "ability": "none"
    },
    {
      "id": 106,
      "name": "Królewicz ropuch",
      "power": 7,
      "description": "",
      "pictureFilename": "nml_toad.webp",
      "faction": 2,
      "range": 2,
      "function": "std",
      "ability": "scorch"
    },
    {
      "id": 107,
      "name": "Kejran",
      "power": 8,
      "description": "",
      "pictureFilename": "nml_kayran.webp",
      "faction": 2,
      "range": 1,
      "function": "hero",
      "ability": "morale"
    },
    {
      "id": 108,
      "name": "Draug",
      "power": 10,
      "description": "",
      "pictureFilename": "nml_draug.webp",
      "faction": 2,
      "range": 1,
      "function": "hero",
      "ability": "none"
    },
    {
      "id": 109,
      "name": "Imlerith",
      "power": 10,
      "description": "",
      "pictureFilename": "nml_imlerith.webp",
      "faction": 2,
      "range": 1,
      "function": "hero",
      "ability": "none"
    },
    {
      "id": 110,
      "name": "Leszy",
      "power": 10,
      "description": "",
      "pictureFilename": "nml_leshan.webp",
      "faction": 2,
      "range": 2,
      "function": "hero",
      "ability": "none"
    },
    {
      "id": 111,
      "name": "Tajemiczny Elf",
      "power": 0,
      "description": "",
      "pictureFilename": "neu_avallach.webp",
      "faction": 2,
      "range": 1,
      "function": "hero",
      "ability": "spy"
    },
    {
      "id": 112,
      "name": "Geralt z Rivii",
      "power": 15,
      "description": "",
      "pictureFilename": "neu_geralt.webp",
      "faction": 2,
      "range": 1,
      "function": "hero",
      "ability": "none"
    },
    {
      "id": 113,
      "name": "Cirilla Fiona Elen Riannon",
      "power": 15,
      "description": "",
      "pictureFilename": "neu_ciri.webp",
      "faction": 2,
      "range": 1,
      "function": "hero",
      "ability": "none"
    },
    {
      "id": 114,
      "name": "Jaskier",
      "power": 2,
      "description": "",
      "pictureFilename": "neu_dandelion.webp",
      "faction": 2,
      "range": 1,
      "function": "std",
      "ability": "horn"
    },
    {
      "id": 115,
      "name": "Emiel Regis Rohellec Terzieff-Godefroy",
      "power": 5,
      "description": "",
      "pictureFilename": "neu_emiel.webp",
      "faction": 2,
      "range": 1,
      "function": "std",
      "ability": "none"
    },
    {
      "id": 116,
      "name": "Triss Merigold",
      "power": 7,
      "description": "",
      "pictureFilename": "neu_triss.webp",
      "faction": 2,
      "range": 1,
      "function": "hero",
      "ability": "none"
    },
    {
      "id": 117,
      "name": "Vesemir",
      "power": 6,
      "description": "",
      "pictureFilename": "neu_vesemir.webp",
      "faction": 2,
      "range": 1,
      "function": "std",
      "ability": "none"
    },
    {
      "id": 118,
      "name": "Villentretenmerth",
      "power": 6,
      "description": "",
      "pictureFilename": "neu_villen.webp",
      "faction": 2,
      "range": 1,
      "function": "std",
      "ability": "scorch"
    },
    {
      "id": 119,
      "name": "Yennefer z Vengerbergu",
      "power": 7,
      "description": "",
      "pictureFilename": "neu_yennefer.webp",
      "faction": 2,
      "range": 2,
      "function": "hero",
      "ability": "medic"
    },
    {
      "id": 120,
      "name": "Zoltan Chivay",
      "power": 5,
      "description": "",
      "pictureFilename": "neu_zoltan.webp",
      "faction": 2,
      "range": 1,
      "function": "std",
      "ability": "none"
    },
    {
      "id": 121,
      "name": "Olgierd von Everec",
      "power": 6,
      "description": "",
      "pictureFilename": "neu_olgierd.webp",
      "faction": 2,
      "range": 1,
      "function": "std",
      "ability": "morale"
    },
    {
      "id": 122,
      "name": "Gaunter O'Dim",
      "power": 2,
      "description": "",
      "pictureFilename": "neu_mrmirror.webp",
      "faction": 2,
      "range": 2,
      "function": "std",
      "ability": "muster"
    },
    {
      "id": 123,
      "name": "Gaunter O'Dim: Cień",
      "power": 4,
      "description": "",
      "pictureFilename": "neu_mrmirror_foglet.webp",
      "faction": 2,
      "range": 1,
      "function": "std",
      "ability": "muster"
    },
    {
      "id": 124,
      "name": "Gaunter O'Dim: Cień",
      "power": 4,
      "description": "",
      "pictureFilename": "neu_mrmirror_foglet.webp",
      "faction": 2,
      "range": 1,
      "function": "std",
      "ability": "muster"
    },
    {
      "id": 125,
      "name": "Gaunter O'Dim: Cień",
      "power": 4,
      "description": "",
      "pictureFilename": "neu_mrmirror_foglet.webp",
      "faction": 2,
      "range": 1,
      "function": "std",
      "ability": "muster"
    },
    {
      "id": 126,
      "name": "Róg Dowódcy",
      "power": 0,
      "description": "",
      "pictureFilename": "spc_horn.webp",
      "faction": 2,
      "range": 0,
      "function": "horn",
      "ability": "none"
    },
    {
      "id": 127,
      "name": "Róg Dowódcy",
      "power": 0,
      "description": "",
      "pictureFilename": "spc_horn.webp",
      "faction": 2,
      "range": 0,
      "function": "horn",
      "ability": "none"
    },
    {
      "id": 128,
      "name": "Róg Dowódcy",
      "power": 0,
      "description": "",
      "pictureFilename": "spc_horn.webp",
      "faction": 2,
      "range": 0,
      "function": "horn",
      "ability": "none"
    },
    {
      "id": 129,
      "name": "Manekin do ćwiczeń",
      "power": 0,
      "description": "",
      "pictureFilename": "spc_dummy.webp",
      "faction": 2,
      "range": 0,
      "function": "decoy",
      "ability": "none"
    },
    {
      "id": 130,
      "name": "Manekin do ćwiczeń",
      "power": 0,
      "description": "",
      "pictureFilename": "spc_dummy.webp",
      "faction": 2,
      "range": 0,
      "function": "decoy",
      "ability": "none"
    },
    {
      "id": 131,
      "name": "Manekin do ćwiczeń",
      "power": 0,
      "description": "",
      "pictureFilename": "spc_dummy.webp",
      "faction": 2,
      "range": 0,
      "function": "decoy",
      "ability": "none"
    },
    {
      "id": 132,
      "name": "Pożoga",
      "power": 0,
      "description": "",
      "pictureFilename": "spc_scorch.webp",
      "faction": 2,
      "range": 0,
      "function": "scorch",
      "ability": "none"
    },
    {
      "id": 133,
      "name": "Pożoga",
      "power": 0,
      "description": "",
      "pictureFilename": "spc_scorch.webp",
      "faction": 2,
      "range": 0,
      "function": "scorch",
      "ability": "none"
    },
    {
      "id": 134,
      "name": "Pożoga",
      "power": 0,
      "description": "",
      "pictureFilename": "spc_scorch.webp",
      "faction": 2,
      "range": 0,
      "function": "scorch",
      "ability": "none"
    },
    {
      "id": 135,
      "name": "Trzaskający mróz",
      "power": 0,
      "description": "",
      "pictureFilename": "spc_frost.webp",
      "faction": 2,
      "range": 0,
      "function": "frost",
      "ability": "none"
    },
    {
      "id": 136,
      "name": "Trzaskający mróz",
      "power": 0,
      "description": "",
      "pictureFilename": "spc_frost.webp",
      "faction": 2,
      "range": 0,
      "function": "frost",
      "ability": "none"
    },
    {
      "id": 137,
      "name": "Trzaskający mróz",
      "power": 0,
      "description": "",
      "pictureFilename": "spc_frost.webp",
      "faction": 2,
      "range": 0,
      "function": "frost",
      "ability": "none"
    },
    {
      "id": 138,
      "name": "Gęsta mgła",
      "power": 0,
      "description": "",
      "pictureFilename": "spc_fog.webp",
      "faction": 2,
      "range": 0,
      "function": "fog",
      "ability": "none"
    },
    {
      "id": 139,
      "name": "Gęsta mgła",
      "power": 0,
      "description": "",
      "pictureFilename": "spc_fog.webp",
      "faction": 2,
      "range": 0,
      "function": "fog",
      "ability": "none"
    },
    {
      "id": 140,
      "name": "Gęsta mgła",
      "power": 0,
      "description": "",
      "pictureFilename": "spc_fog.webp",
      "faction": 2,
      "range": 0,
      "function": "fog",
      "ability": "none"
    },
    {
      "id": 141,
      "name": "Czyste niebo",
      "power": 0,
      "description": "",
      "pictureFilename": "spc_clearsky.webp",
      "faction": 2,
      "range": 0,
      "function": "clear",
      "ability": "none"
    },
    {
      "id": 142,
      "name": "Czyste niebo",
      "power": 0,
      "description": "",
      "pictureFilename": "spc_clearsky.webp",
      "faction": 2,
      "range": 0,
      "function": "clear",
      "ability": "none"
    },
    {
      "id": 143,
      "name": "Czyste niebo",
      "power": 0,
      "description": "",
      "pictureFilename": "spc_clearsky.webp",
      "faction": 2,
      "range": 0,
      "function": "clear",
      "ability": "none"
    },
    {
      "id": 144,
      "name": "Wsparcie oblężnicze",
      "power": 0,
      "description": "",
      "pictureFilename": "nil_siege_support.webp",
      "faction": 3,
      "range": 2,
      "function": "std",
      "ability": "medic"
    },
    {
      "id": 145,
      "name": "Wsparcie łuczników",
      "power": 1,
      "description": "",
      "pictureFilename": "nil_archer_support.webp",
      "faction": 3,
      "range": 2,
      "function": "std",
      "ability": "medic"
    },
    {
      "id": 146,
      "name": "Wsparcie łuczników",
      "power": 1,
      "description": "",
      "pictureFilename": "nil_archer_support_1.webp",
      "faction": 3,
      "range": 2,
      "function": "std",
      "ability": "medic"
    },
    {
      "id": 147,
      "name": "Albrich",
      "power": 2,
      "description": "",
      "pictureFilename": "nil_albrich.webp",
      "faction": 3,
      "range": 2,
      "function": "std",
      "ability": "none"
    },
    {
      "id": 148,
      "name": "Kawaleria Nauzicaa",
      "power": 2,
      "description": "",
      "pictureFilename": "nil_nauzicaa.webp",
      "faction": 3,
      "range": 1,
      "function": "std",
      "ability": "bond"
    },
    {
      "id": 149,
      "name": "Kawaleria Nauzicaa",
      "power": 2,
      "description": "",
      "pictureFilename": "nil_nauzicaa_1.webp",
      "faction": 3,
      "range": 1,
      "function": "std",
      "ability": "bond"
    },
    {
      "id": 150,
      "name": "Kawaleria Nauzicaa",
      "power": 2,
      "description": "",
      "pictureFilename": "nil_nauzicaa_2.webp",
      "faction": 3,
      "range": 1,
      "function": "std",
      "ability": "bond"
    },
    {
      "id": 151,
      "name": "Sweers",
      "power": 2,
      "description": "",
      "pictureFilename": "nil_sweers.webp",
      "faction": 3,
      "range": 2,
      "function": "std",
      "ability": "none"
    },
    {
      "id": 152,
      "name": "Vreemde",
      "power": 2,
      "description": "",
      "pictureFilename": "nil_vreemde.webp",
      "faction": 3,
      "range": 1,
      "function": "std",
      "ability": "none"
    },
    {
      "id": 153,
      "name": "Brygada Impera",
      "power": 3,
      "description": "",
      "pictureFilename": "nil_impera_brigade.webp",
      "faction": 3,
      "range": 1,
      "function": "std",
      "ability": "bond"
    },
    {
      "id": 154,
      "name": "Brygada Impera",
      "power": 3,
      "description": "",
      "pictureFilename": "nil_impera_brigade_1.webp",
      "faction": 3,
      "range": 1,
      "function": "std",
      "ability": "bond"
    },
    {
      "id": 155,
      "name": "Brygada Impera",
      "power": 3,
      "description": "",
      "pictureFilename": "nil_impera_brigade_2.webp",
      "faction": 3,
      "range": 1,
      "function": "std",
      "ability": "bond"
    },
    {
      "id": 156,
      "name": "Brygada Impera",
      "power": 3,
      "description": "",
      "pictureFilename": "nil_impera_brigade_3.webp",
      "faction": 3,
      "range": 1,
      "function": "std",
      "ability": "bond"
    },
    {
      "id": 157,
      "name": "Morteisen",
      "power": 3,
      "description": "",
      "pictureFilename": "nil_morteisen.webp",
      "faction": 3,
      "range": 1,
      "function": "std",
      "ability": "none"
    },
    {
      "id": 158,
      "name": "Puttkammer",
      "power": 3,
      "description": "",
      "pictureFilename": "nil_puttkammer.webp",
      "faction": 3,
      "range": 2,
      "function": "std",
      "ability": "none"
    },
    {
      "id": 159,
      "name": "Zdezelowana mangonela",
      "power": 3,
      "description": "",
      "pictureFilename": "nil_rotten.webp",
      "faction": 3,
      "range": 2,
      "function": "std",
      "ability": "none"
    },
    {
      "id": 160,
      "name": "Cynthia",
      "power": 4,
      "description": "",
      "pictureFilename": "nil_cynthia.webp",
      "faction": 3,
      "range": 2,
      "function": "std",
      "ability": "none"
    },
    {
      "id": 161,
      "name": "Rainfarn",
      "power": 4,
      "description": "",
      "pictureFilename": "nil_rainfarn.webp",
      "faction": 3,
      "range": 1,
      "function": "std",
      "ability": "none"
    },
    {
      "id": 162,
      "name": "Vanhemar",
      "power": 4,
      "description": "",
      "pictureFilename": "nil_vanhemar.webp",
      "faction": 3,
      "range": 2,
      "function": "std",
      "ability": "none"
    },
    {
      "id": 163,
      "name": "Vattier de Rideaux",
      "power": 4,
      "description": "",
      "pictureFilename": "nil_vattier.webp",
      "faction": 3,
      "range": 1,
      "function": "std",
      "ability": "spy"
    },
    {
      "id": 164,
      "name": "Renuald aep Matsen",
      "power": 5,
      "description": "",
      "pictureFilename": "nil_renuald.webp",
      "faction": 3,
      "range": 2,
      "function": "std",
      "ability": "none"
    },
    {
      "id": 165,
      "name": "Młody emisariusz",
      "power": 5,
      "description": "",
      "pictureFilename": "nil_young_emissary.webp",
      "faction": 3,
      "range": 1,
      "function": "std",
      "ability": "bond"
    },
    {
      "id": 166,
      "name": "Młody emisariusz",
      "power": 5,
      "description": "",
      "pictureFilename": "nil_young_emissary_1.webp",
      "faction": 3,
      "range": 1,
      "function": "std",
      "ability": "bond"
    },
    {
      "id": 167,
      "name": "Zerrikański Ognisty Skorpion",
      "power": 5,
      "description": "",
      "pictureFilename": "nil_zerri.webp",
      "faction": 3,
      "range": 2,
      "function": "std",
      "ability": "none"
    },
    {
      "id": 168,
      "name": "Assire van Anahid",
      "power": 6,
      "description": "",
      "pictureFilename": "nil_assire.webp",
      "faction": 3,
      "range": 2,
      "function": "std",
      "ability": "none"
    },
    {
      "id": 169,
      "name": "Cahir Mawr Dyffryn aep Ceallach",
      "power": 6,
      "description": "",
      "pictureFilename": "nil_cahir.webp",
      "faction": 3,
      "range": 1,
      "function": "std",
      "ability": "none"
    },
    {
      "id": 170,
      "name": "Fringilla Vigo",
      "power": 6,
      "description": "",
      "pictureFilename": "nil_fringilla.webp",
      "faction": 3,
      "range": 2,
      "function": "std",
      "ability": "none"
    },
    {
      "id": 171,
      "name": "Saper",
      "power": 6,
      "description": "",
      "pictureFilename": "nil_siege_engineer.webp",
      "faction": 3,
      "range": 2,
      "function": "std",
      "ability": "none"
    },
    {
      "id": 172,
      "name": "Shilard Fitz-Oesterlen",
      "power": 7,
      "description": "",
      "pictureFilename": "nil_shilard.webp",
      "faction": 3,
      "range": 1,
      "function": "std",
      "ability": "spy"
    },
    {
      "id": 173,
      "name": "Stefan Skellen",
      "power": 9,
      "description": "",
      "pictureFilename": "nil_stefan.webp",
      "faction": 3,
      "range": 1,
      "function": "std",
      "ability": "spy"
    },
    {
      "id": 174,
      "name": "Nilfgaardzki łucznik",
      "power": 10,
      "description": "",
      "pictureFilename": "nil_black_archer.webp",
      "faction": 3,
      "range": 2,
      "function": "std",
      "ability": "none"
    },
    {
      "id": 175,
      "name": "Nilfgaardzki łucznik",
      "power": 10,
      "description": "",
      "pictureFilename": "nil_black_archer_1.webp",
      "faction": 3,
      "range": 2,
      "function": "std",
      "ability": "none"
    },
    {
      "id": 176,
      "name": "Wielki Ognisty Skorpion",
      "power": 10,
      "description": "",
      "pictureFilename": "nil_heavy_zerri.webp",
      "faction": 3,
      "range": 2,
      "function": "std",
      "ability": "none"
    },
    {
      "id": 177,
      "name": "Letho z Gulety",
      "power": 10,
      "description": "",
      "pictureFilename": "nil_letho.webp",
      "faction": 3,
      "range": 1,
      "function": "hero",
      "ability": "none"
    },
    {
      "id": 178,
      "name": "Menno Coehoorn",
      "power": 10,
      "description": "",
      "pictureFilename": "nil_menno.webp",
      "faction": 3,
      "range": 1,
      "function": "hero",
      "ability": "medic"
    },
    {
      "id": 179,
      "name": "Morvran Voorhis",
      "power": 10,
      "description": "",
      "pictureFilename": "nil_moorvran.webp",
      "faction": 3,
      "range": 2,
      "function": "hero",
      "ability": "none"
    },
    {
      "id": 180,
      "name": "Tibor Eggebracht",
      "power": 10,
      "description": "",
      "pictureFilename": "nil_tibor.webp",
      "faction": 3,
      "range": 2,
      "function": "hero",
      "ability": "none"
    },
    {
      "id": 181,
      "name": "Tajemiczny Elf",
      "power": 0,
      "description": "",
      "pictureFilename": "neu_avallach.webp",
      "faction": 3,
      "range": 1,
      "function": "hero",
      "ability": "spy"
    },
    {
      "id": 182,
      "name": "Geralt z Rivii",
      "power": 15,
      "description": "",
      "pictureFilename": "neu_geralt.webp",
      "faction": 3,
      "range": 1,
      "function": "hero",
      "ability": "none"
    },
    {
      "id": 183,
      "name": "Cirilla Fiona Elen Riannon",
      "power": 15,
      "description": "",
      "pictureFilename": "neu_ciri.webp",
      "faction": 3,
      "range": 1,
      "function": "hero",
      "ability": "none"
    },
    {
      "id": 184,
      "name": "Jaskier",
      "power": 2,
      "description": "",
      "pictureFilename": "neu_dandelion.webp",
      "faction": 3,
      "range": 1,
      "function": "std",
      "ability": "horn"
    },
    {
      "id": 185,
      "name": "Emiel Regis Rohellec Terzieff-Godefroy",
      "power": 5,
      "description": "",
      "pictureFilename": "neu_emiel.webp",
      "faction": 3,
      "range": 1,
      "function": "std",
      "ability": "none"
    },
    {
      "id": 186,
      "name": "Triss Merigold",
      "power": 7,
      "description": "",
      "pictureFilename": "neu_triss.webp",
      "faction": 3,
      "range": 1,
      "function": "hero",
      "ability": "none"
    },
    {
      "id": 187,
      "name": "Vesemir",
      "power": 6,
      "description": "",
      "pictureFilename": "neu_vesemir.webp",
      "faction": 3,
      "range": 1,
      "function": "std",
      "ability": "none"
    },
    {
      "id": 188,
      "name": "Villentretenmerth",
      "power": 6,
      "description": "",
      "pictureFilename": "neu_villen.webp",
      "faction": 3,
      "range": 1,
      "function": "std",
      "ability": "scorch"
    },
    {
      "id": 189,
      "name": "Yennefer z Vengerbergu",
      "power": 7,
      "description": "",
      "pictureFilename": "neu_yennefer.webp",
      "faction": 3,
      "range": 2,
      "function": "hero",
      "ability": "medic"
    },
    {
      "id": 190,
      "name": "Zoltan Chivay",
      "power": 5,
      "description": "",
      "pictureFilename": "neu_zoltan.webp",
      "faction": 3,
      "range": 1,
      "function": "std",
      "ability": "none"
    },
    {
      "id": 191,
      "name": "Olgierd von Everec",
      "power": 6,
      "description": "",
      "pictureFilename": "neu_olgierd.webp",
      "faction": 3,
      "range": 1,
      "function": "std",
      "ability": "morale"
    },
    {
      "id": 192,
      "name": "Gaunter O'Dim",
      "power": 2,
      "description": "",
      "pictureFilename": "neu_mrmirror.webp",
      "faction": 3,
      "range": 2,
      "function": "std",
      "ability": "muster"
    },
    {
      "id": 193,
      "name": "Gaunter O'Dim: Cień",
      "power": 4,
      "description": "",
      "pictureFilename": "neu_mrmirror_foglet.webp",
      "faction": 3,
      "range": 1,
      "function": "std",
      "ability": "muster"
    },
    {
      "id": 194,
      "name": "Gaunter O'Dim: Cień",
      "power": 4,
      "description": "",
      "pictureFilename": "neu_mrmirror_foglet.webp",
      "faction": 3,
      "range": 1,
      "function": "std",
      "ability": "muster"
    },
    {
      "id": 195,
      "name": "Gaunter O'Dim: Cień",
      "power": 4,
      "description": "",
      "pictureFilename": "neu_mrmirror_foglet.webp",
      "faction": 3,
      "range": 1,
      "function": "std",
      "ability": "muster"
    },
    {
      "id": 196,
      "name": "Róg Dowódcy",
      "power": 0,
      "description": "",
      "pictureFilename": "spc_horn.webp",
      "faction": 3,
      "range": 0,
      "function": "horn",
      "ability": "none"
    },
    {
      "id": 197,
      "name": "Róg Dowódcy",
      "power": 0,
      "description": "",
      "pictureFilename": "spc_horn.webp",
      "faction": 3,
      "range": 0,
      "function": "horn",
      "ability": "none"
    },
    {
      "id": 198,
      "name": "Róg Dowódcy",
      "power": 0,
      "description": "",
      "pictureFilename": "spc_horn.webp",
      "faction": 3,
      "range": 0,
      "function": "horn",
      "ability": "none"
    },
    {
      "id": 199,
      "name": "Manekin do ćwiczeń",
      "power": 0,
      "description": "",
      "pictureFilename": "spc_dummy.webp",
      "faction": 3,
      "range": 0,
      "function": "decoy",
      "ability": "none"
    },
    {
      "id": 200,
      "name": "Manekin do ćwiczeń",
      "power": 0,
      "description": "",
      "pictureFilename": "spc_dummy.webp",
      "faction": 3,
      "range": 0,
      "function": "decoy",
      "ability": "none"
    },
    {
      "id": 201,
      "name": "Manekin do ćwiczeń",
      "power": 0,
      "description": "",
      "pictureFilename": "spc_dummy.webp",
      "faction": 3,
      "range": 0,
      "function": "decoy",
      "ability": "none"
    },
    {
      "id": 202,
      "name": "Pożoga",
      "power": 0,
      "description": "",
      "pictureFilename": "spc_scorch.webp",
      "faction": 3,
      "range": 0,
      "function": "scorch",
      "ability": "none"
    },
    {
      "id": 203,
      "name": "Pożoga",
      "power": 0,
      "description": "",
      "pictureFilename": "spc_scorch.webp",
      "faction": 3,
      "range": 0,
      "function": "scorch",
      "ability": "none"
    },
    {
      "id": 204,
      "name": "Pożoga",
      "power": 0,
      "description": "",
      "pictureFilename": "spc_scorch.webp",
      "faction": 3,
      "range": 0,
      "function": "scorch",
      "ability": "none"
    },
    {
      "id": 205,
      "name": "Trzaskający mróz",
      "power": 0,
      "description": "",
      "pictureFilename": "spc_frost.webp",
      "faction": 3,
      "range": 0,
      "function": "frost",
      "ability": "none"
    },
    {
      "id": 206,
      "name": "Trzaskający mróz",
      "power": 0,
      "description": "",
      "pictureFilename": "spc_frost.webp",
      "faction": 3,
      "range": 0,
      "function": "frost",
      "ability": "none"
    },
    {
      "id": 207,
      "name": "Trzaskający mróz",
      "power": 0,
      "description": "",
      "pictureFilename": "spc_frost.webp",
      "faction": 3,
      "range": 0,
      "function": "frost",
      "ability": "none"
    },
    {
      "id": 208,
      "name": "Gęsta mgła",
      "power": 0,
      "description": "",
      "pictureFilename": "spc_fog.webp",
      "faction": 3,
      "range": 0,
      "function": "fog",
      "ability": "none"
    },
    {
      "id": 209,
      "name": "Gęsta mgła",
      "power": 0,
      "description": "",
      "pictureFilename": "spc_fog.webp",
      "faction": 3,
      "range": 0,
      "function": "fog",
      "ability": "none"
    },
    {
      "id": 210,
      "name": "Gęsta mgła",
      "power": 0,
      "description": "",
      "pictureFilename": "spc_fog.webp",
      "faction": 3,
      "range": 0,
      "function": "fog",
      "ability": "none"
    },
    {
      "id": 211,
      "name": "Czyste niebo",
      "power": 0,
      "description": "",
      "pictureFilename": "spc_clearsky.webp",
      "faction": 3,
      "range": 0,
      "function": "clear",
      "ability": "none"
    },
    {
      "id": 212,
      "name": "Czyste niebo",
      "power": 0,
      "description": "",
      "pictureFilename": "spc_clearsky.webp",
      "faction": 3,
      "range": 0,
      "function": "clear",
      "ability": "none"
    },
    {
      "id": 213,
      "name": "Czyste niebo",
      "power": 0,
      "description": "",
      "pictureFilename": "spc_clearsky.webp",
      "faction": 3,
      "range": 0,
      "function": "clear",
      "ability": "none"
    }
  ]
}